matplotlib_multicolored_line/__init__.py
matplotlib_multicolored_line/_main.py
matplotlib_multicolored_line/py.typed
matplotlib_multicolored_line-0.3.0.dist-info/licenses/LICENSE
matplotlib_multicolored_line-0.3.0.dist-info/METADATA
matplotlib_multicolored_line-0.3.0.dist-info/WHEEL
matplotlib_multicolored_line-0.3.0.dist-info/top_level.txt
matplotlib_multicolored_line-0.3.0.dist-info/RECORD
