Metadata-Version: 2.4
Name: matplotlib-multicolored-line
Version: 0.3.0
Summary: Plot multicolored lines in Matplotlib
Author-email: 34j <34j.95a2p@simplelogin.com>
License-Expression: CC0-1.0
Project-URL: Bug Tracker, https://github.com/34j/matplotlib-multicolored-line/issues
Project-URL: Changelog, https://github.com/34j/matplotlib-multicolored-line/blob/main/CHANGELOG.md
Project-URL: documentation, https://matplotlib-multicolored-line.readthedocs.io
Project-URL: repository, https://github.com/34j/matplotlib-multicolored-line
Classifier: Development Status :: 2 - Pre-Alpha
Classifier: Intended Audience :: Developers
Classifier: Natural Language :: English
Classifier: Operating System :: OS Independent
Classifier: Programming Language :: Python :: 3.9
Classifier: Programming Language :: Python :: 3.10
Classifier: Programming Language :: Python :: 3.11
Classifier: Programming Language :: Python :: 3.12
Classifier: Programming Language :: Python :: 3.13
Classifier: Topic :: Software Development :: Libraries
Requires-Python: >=3.9
License-File: LICENSE
Requires-Dist: matplotlib>=3.9.4
Dynamic: license-file
